heatcontrol/__init__.py
heatcontrol/spot_price_control.py
heatcontrol-0.6.5.dist-info/entry_points.txt
heatcontrol-0.6.5.dist-info/LICENSE
heatcontrol-0.6.5.dist-info/WHEEL
heatcontrol-0.6.5.dist-info/METADATA
heatcontrol-0.6.5.dist-info/RECORD
