Metadata-Version: 2.1
Name: heatcontrol
Version: 0.6.5
Summary: 
Author: Rami Rahikkala
Author-email: rami.rahikkala@gmail.fi
Requires-Python: >=3.9,<4.0
Classifier: Programming Language :: Python :: 3
Classifier: Programming Language :: Python :: 3.9
Classifier: Programming Language :: Python :: 3.10
Classifier: Programming Language :: Python :: 3.11
Requires-Dist: mock-gpio (>=0.1.8,<0.2.0)
Requires-Dist: requests (>=2.28.2,<3.0.0)
Requires-Dist: rpi-gpio (>=0.7.1,<0.8.0)
Requires-Dist: schedule (>=1.1.0,<2.0.0)
